cut_finder/__init__.py
cut_finder/__main__.py
cut_finder/board_sets.py
cut_finder/boards.py
cut_finder/cutfinder.py
cut_finder/test/__init__.py
cut_finder/test/cut_finder_test.py
cut_finder/utils/__init__.py
cut_finder/utils/board_sets.py
cut_finder/utils/boards.py
cut_finder/utils/utils.py
cutfinder/__init__.py
cutfinder/__main__.py
cutfinder/cutfinder.py
cutfinder/test/__init__.py
cutfinder/test/cut_finder_test.py
cutfinder/utils/__init__.py
cutfinder/utils/board_sets.py
cutfinder/utils/boards.py
cutfinder/utils/utils.py
cutfinder-0.1.3.dist-info/LICENSE
cutfinder-0.1.3.dist-info/METADATA
cutfinder-0.1.3.dist-info/WHEEL
cutfinder-0.1.3.dist-info/entry_points.txt
cutfinder-0.1.3.dist-info/top_level.txt
cutfinder-0.1.3.dist-info/RECORD
