Metadata-Version: 2.1
Name: cutfinder
Version: 0.1.3
Summary: Plan lumber cutting schemes with minimal waste
Home-page: https://github.com/Cluff1112/cut_finder
Author: Cory Cluff
Author-email: cluff.cory@gmail.com
License: MIT
Platform: UNKNOWN
Classifier: License :: OSI Approved :: MIT License
Classifier: Programming Language :: Python :: 3
Classifier: Programming Language :: Python :: 3.7
Requires-Dist: setuptools
